wg_config_generator/__init__.py
wg_config_generator/config.py
wg_config_generator/generator.py
wg_config_generator/main.py
wg_config_generator/tools.py
wg_config_generator-0.1.0.dist-info/entry_points.txt
wg_config_generator-0.1.0.dist-info/LICENSE
wg_config_generator-0.1.0.dist-info/WHEEL
wg_config_generator-0.1.0.dist-info/METADATA
wg_config_generator-0.1.0.dist-info/RECORD
