Metadata-Version: 2.1
Name: wg-config-generator
Version: 0.1.0
Summary: Wireguard Config Generator
License: MIT
Author: Oliver Burghard
Author-email: info@oliver-burghard.de
Requires-Python: >=3.6.1,<4.0.0
Classifier: License :: OSI Approved :: MIT License
Classifier: Programming Language :: Python :: 3
Classifier: Programming Language :: Python :: 3.7
Classifier: Programming Language :: Python :: 3.8
Classifier: Programming Language :: Python :: 3.9
Requires-Dist: PyYAML (>=5.4.1,<6.0.0)
Requires-Dist: attrs (>=21.2.0,<22.0.0)
Requires-Dist: click (>=8.0.1,<9.0.0)
